<?xml version="1.0" encoding="UTF-8" standalone="no"?><Date date="2012-12-28"><Message type="TopicMessage"><Id>1356704555591-1</Id><Title>MLNX stock long strong bullish today</Title><Msg>long strong</Msg><Username>A Yahoo! User</Username><Timestamp>1356704555591</Timestamp><DateTime>Fri, 2012-12-28 09:22:35 EST</DateTime><ThumbUp>0</ThumbUp><ThumbDown>2</ThumbDown><Sentiment/></Message><Message type="ReplyMessage"><Id>1356711756431-2</Id><Topic><Title>New info about KO.</Title><Username>franklangston96</Username><Timestamp>1356709379512</Timestamp><DateTime>Fri, 2012-12-28 10:42:59 EST</DateTime></Topic><Msg>Thanks very much !</Msg><Username>petersen.effie</Username><Timestamp>1356711756431</Timestamp><DateTime>Fri, 2012-12-28 11:22:36 EST</DateTime><ThumbUp>0</ThumbUp><ThumbDown>1</ThumbDown><Sentiment/></Message><Message type="ReplyMessage"><Id>1356712021502-3</Id><Topic><Title>useful information for shareholders</Title><Username>virginiafrancis710</Username><Timestamp>1356533510317</Timestamp><DateTime>Wed, 2012-12-26 09:51:50 EST</DateTime></Topic><Msg>Thanks very much !</Msg><Username>petersen.effie</Username><Timestamp>1356712021502</Timestamp><DateTime>Fri, 2012-12-28 11:27:01 EST</DateTime><ThumbUp>0</ThumbUp><ThumbDown>2</ThumbDown><Sentiment/></Message><Message type="ReplyMessage"><Id>1356712723080-4</Id><Topic><Title>New info about KO.</Title><Username>franklangston96</Username><Timestamp>1356709379512</Timestamp><DateTime>Fri, 2012-12-28 10:42:59 EST</DateTime></Topic><Msg>amazing news</Msg><Username>willardjones927</Username><Timestamp>1356712723080</Timestamp><DateTime>Fri, 2012-12-28 11:38:43 EST</DateTime><ThumbUp>0</ThumbUp><ThumbDown>1</ThumbDown><Sentiment>Buy</Sentiment></Message><Message type="ReplyMessage"><Id>1356713026503-5</Id><Topic><Title>useful information for shareholders</Title><Username>virginiafrancis710</Username><Timestamp>1356533510317</Timestamp><DateTime>Wed, 2012-12-26 09:51:50 EST</DateTime></Topic><Msg>amazing news</Msg><Username>willardjones927</Username><Timestamp>1356713026503</Timestamp><DateTime>Fri, 2012-12-28 11:43:46 EST</DateTime><ThumbUp>0</ThumbUp><ThumbDown>2</ThumbDown><Sentiment/></Message><Message type="TopicMessage"><Id>1356715498151-6</Id><Title>KO has a problem being a new Competitor</Title><Msg>Symbol Soda... Coke will not be able to grow the at home market in markets that Sodastream is in. IMO....I'm estimating Sodsatream sold 600,000 machines this xmas vs 300,000 in the USA. Next year they will sell 1M plus during xmas. The Sodastream stuff taste better.... IMO</Msg><Username>tejdem1</Username><Timestamp>1356715498151</Timestamp><DateTime>Fri, 2012-12-28 12:24:58 EST</DateTime><ThumbUp>2</ThumbUp><ThumbDown>14</ThumbDown><Sentiment/></Message><Message type="TopicMessage"><Id>1356724823105-7</Id><Title>2009</Title><Msg>lowest price in last pre split Mar 5, 2009 open 39.16 high 39.44 low 37.44 close 37.85 Stock is a buy</Msg><Username>mmck1961</Username><Timestamp>1356724823105</Timestamp><DateTime>Fri, 2012-12-28 15:00:23 EST</DateTime><ThumbUp>0</ThumbUp><ThumbDown>0</ThumbDown><Sentiment>Strong Buy</Sentiment></Message><Message type="ReplyMessage"><Id>1356724840847-8</Id><Topic><Title>2009</Title><Username>mmck1961</Username><Timestamp>1356724823105</Timestamp><DateTime>Fri, 2012-12-28 15:00:23 EST</DateTime></Topic><Msg>A STRONG BUY</Msg><Username>mmck1961</Username><Timestamp>1356724840847</Timestamp><DateTime>Fri, 2012-12-28 15:00:40 EST</DateTime><ThumbUp>0</ThumbUp><ThumbDown>1</ThumbDown><Sentiment>Strong Buy</Sentiment></Message><Message type="ReplyMessage"><Id>1356725133574-9</Id><Topic><Title>Buying more Monday</Title><Username>dsc20601</Username><Timestamp>1355583531465</Timestamp><DateTime>Sat, 2012-12-15 09:58:51 EST</DateTime></Topic><Msg>bought a little more @ 36.10 cheap cheap cheap</Msg><Username>mmck1961</Username><Timestamp>1356725133574</Timestamp><DateTime>Fri, 2012-12-28 15:05:33 EST</DateTime><ThumbUp>2</ThumbUp><ThumbDown>1</ThumbDown><Sentiment>Strong Buy</Sentiment></Message><Message type="ReplyMessage"><Id>1356727955031-10</Id><Topic><Title>Buying more Monday</Title><Username>dsc20601</Username><Timestamp>1355583531465</Timestamp><DateTime>Sat, 2012-12-15 09:58:51 EST</DateTime></Topic><Msg>bought again at 35.95</Msg><Username>mmck1961</Username><Timestamp>1356727955031</Timestamp><DateTime>Fri, 2012-12-28 15:52:35 EST</DateTime><ThumbUp>2</ThumbUp><ThumbDown>1</ThumbDown><Sentiment>Strong Buy</Sentiment></Message></Date>